acons.py
acons-0.1.dist-info/LICENSE.txt
acons-0.1.dist-info/METADATA
acons-0.1.dist-info/WHEEL
acons-0.1.dist-info/top_level.txt
acons-0.1.dist-info/RECORD
