Metadata-Version: 2.1
Name: acons
Version: 0.1
Summary: Async command-line runner
Home-page: https://github.com/boscoh/acons
Author: Bosco Ho
Author-email: apposite@gmail.com
License: MIT
Platform: UNKNOWN
Classifier: Development Status :: 4 - Beta
Classifier: Programming Language :: Python :: 3
Classifier: Intended Audience :: Developers
Classifier: License :: OSI Approved :: MIT License
Classifier: Topic :: Software Development :: Libraries
Classifier: Topic :: Utilities
Requires-Dist: fastapi
Requires-Dist: uvicorn
Requires-Dist: pylru
